{
  "paper_id": "MCS116_2026_MIDSEM",
  "paper_metadata": {
    "subject_code": "MCS116",
    "subject_name": "Computer Vision",
    "program": "M. Tech AI &DS",
    "semester": 2,
    "academic_year": "2025-2026",
    "exam_type": "MidSem",
    "exam_name": "Mid-Term Examination",
    "exam_mode": "Offline",
    "time_duration": "1 ½Hours",
    "max_marks": 30
  },
  "questions": [
    {
      "question_id": "Q1",
      "unit": null,
      "question_text": "Attempt all parts.",
      "marks": 10.0,
      "subparts": [
        {
          "subpart_id": "a",
          "text": "Discuss the properties of Bidirectional Reflection Distribution Function .",
          "marks": 2.5
        },
        {
          "subpart_id": "b",
          "text": "Explain how Bayesian formulation reflects the inverse relationship between computer vision and computer graphics.",
          "marks": 2.5
        },
        {
          "subpart_id": "c",
          "text": "Why is image preprocessing an essential step in computer vision applications?",
          "marks": 2.5
        },
        {
          "subpart_id": "d",
          "text": "A calibrated stereo camera system is being used to estimate the position of a point in a 3D scene. The camera has a focal length of 800 pixels along the x-axis. When observing a particular point, the disparity is measured to be 40 pixels, and the depth of this point from the camera system along the Z-axis is 4 meters. Calculate the baseline distance between the two cameras. Additionally, if the depth increases to 6 meters, what will happen to the disparity? Explain.",
          "marks": 2.5
        }
      ]
    },
    {
      "question_id": "Q2",
      "unit": "UNIT I",
      "question_text": "Attempt all parts.",
      "marks": 10.0,
      "subparts": [
        {
          "subpart_id": "a",
          "text": "Consider a computer vision system in an autonomous vehicle. Describe how the system processes the visual information step by step, from analyzing the image to making a driving decision.",
          "marks": 3.3333333333333335
        },
        {
          "subpart_id": "b",
          "text": "Derive an expression for the relationship between the radiance emitted or reflected from the scene and the irradiance measured at the camera sensor.",
          "marks": 3.3333333333333335
        },
        {
          "subpart_id": "c",
          "text": "Write short notes on any two application of computer vision.",
          "marks": 3.3333333333333335
        }
      ]
    },
    {
      "question_id": "Q3",
      "unit": "UNIT II",
      "question_text": "Attempt all parts.",
      "marks": 10.0,
      "subparts": [
        {
          "subpart_id": "a",
          "text": "Explain the difference between continuous images and discrete images. Discuss the roles of sampling and quantization in this process.",
          "marks": 3.3333333333333335
        },
        {
          "subpart_id": "b",
          "text": "Discuss the significance of gradient computation and non- maximum suppression in detecting edges. Suppose you apply the Sobel operator to a point in an image, and the gradient values in the x and y directions are Gx=3 and Gy=4. Calculate the magnitude and direction of the gradient at this point.",
          "marks": 3.3333333333333335
        },
        {
          "subpart_id": "c",
          "text": "Explain the concept of optical flow in computer vision. How does it represent motion in a video sequence? In a video sequence, a small object moves across the image plane. At a particular pixel location the image intensity gradients are given by 𝜕𝐼 𝜕𝑦= 7, 𝜕𝐼 𝜕𝑥= 3 𝑎𝑛𝑑 𝜕𝐼 𝜕𝑡= −1.Determine the relationship between velocity components of the pixel in the x and y directions at this point.",
          "marks": 3.3333333333333335
        }
      ]
    }
  ]
}